{
  "indexes": [
    {
      "collectionGroup": "projectSubmissions",
      "queryScope": "COLLECTION",
      "fields": [
        {
          "fieldPath": "userId",
          "order": "ASCENDING"
        },
        {
          "fieldPath": "courseId",
          "order": "ASCENDING"
        }
      ]
    },
    {
      "collectionGroup": "projectSubmissions",
      "queryScope": "COLLECTION",
      "fields": [
        {
          "fieldPath": "status",
          "order": "ASCENDING"
        },
        {
          "fieldPath": "submittedAt",
          "order": "DESCENDING"
        }
      ]
    },
    {
      "collectionGroup": "projectSubmissions",
      "queryScope": "COLLECTION",
      "fields": [
        {
          "fieldPath": "courseId",
          "order": "ASCENDING"
        },
        {
          "fieldPath": "submittedAt",
          "order": "DESCENDING"
        }
      ]
    },
    {
      "collectionGroup": "courseProgress",
      "queryScope": "COLLECTION",
      "fields": [
        {
          "fieldPath": "userId",
          "order": "ASCENDING"
        },
        {
          "fieldPath": "courseId",
          "order": "ASCENDING"
        }
      ]
    }
  ],
  "fieldOverrides": []
}